[
  {
    "id": "雷峰网-0deef6cc",
    "title": "AI原生的6G，为什么是高通近20年最大的机会？",
    "url": "https://www.leiphone.com/category/chips/FkmtxEJsPCPpVC1v.html",
    "source": "雷峰网",
    "summary": "高通在MWC2026推动AI原生6G，预计2029年商用，将成20年来最大机遇",
    "category": "技术",
    "tags": [
      "6G",
      "高通",
      "AI原生",
      "移动通信",
      "通感一体",
      "边缘计算"
    ]
  },
  {
    "id": "雷峰网-5947ddd2",
    "title": "易点天下「可见性峰会」圆满收官，以GEO+GEM构筑AI时代品牌全球化护城河",
    "url": "https://www.leiphone.com/category/industrynews/7T5R0aIBcn5PqAUE.html",
    "source": "雷峰网",
    "summary": "易点天下举办可见性峰会，探讨AI时代品牌全球化与GEO营销策略",
    "category": "商业",
    "tags": [
      "AI营销",
      "品牌出海",
      "GEO",
      "智能营销",
      "行业峰会"
    ]
  },
  {
    "id": "雷峰网-acf09300",
    "title": "千问AI眼镜G1爆卖！3小时全平台登顶第一、部分渠道已售罄",
    "url": "https://www.leiphone.com/category/industrynews/ZUMbCfjunVUDdGhU.html",
    "source": "雷峰网",
    "summary": "千问AI眼镜G1于3月8日发售，3小时登顶全平台热销榜，部分渠道售罄，售价2899元起",
    "category": "产品",
    "tags": [
      "千问",
      "AI眼镜",
      "G1",
      "智能眼镜",
      "新品发售"
    ]
  }
]